EVONOMAD/__init__.py
EVONOMAD/core.py
EVONOMAD/__pycache__/__init__.cpython-310.pyc
EVONOMAD/__pycache__/__init__.cpython-312.pyc
EVONOMAD/__pycache__/core.cpython-310.pyc
EVONOMAD/__pycache__/core.cpython-312.pyc
evonomad-0.1.0.dist-info/licenses/LICENSE
evonomad-0.1.0.dist-info/METADATA
evonomad-0.1.0.dist-info/WHEEL
evonomad-0.1.0.dist-info/top_level.txt
evonomad-0.1.0.dist-info/RECORD
